<?xml version="1.0" encoding="UTF-8"?>
<config xmlns="urn:ietf:params:xml:ns:netconf:base:1.0"
	xmlns:ianadns="http://www.nic.cz/ns/yang/iana-dns-parameters">
  <zones xmlns="http://www.nic.cz/ns/yang/dns-zones">
    <zone>
      <name>example</name>
      <class>IN</class>
      <description>
	This zone comes from RFC 4035.
      </description>
      <rrset>
	<owner>example</owner>
	<type>ianadns:SOA</type>
	<ttl>3600</ttl>
	<rdata>
	  <id>1</id>
	  <soa>
	    <mname>ns1</mname>
	    <rname>bugs.x.w.example</rname>
	    <serial>1081539377</serial>
	    <refresh>3600</refresh>
	    <retry>300</retry>
	    <expire>3600000</expire>
	    <minimum>3600</minimum>
	  </soa>
	</rdata>
      </rrset>
      <rrset>
	<owner>example</owner>
	<type>ianadns:NS</type>
	<ttl>3600</ttl>
	<rdata>
	  <id>1</id>
	  <ns>
	    <nsdname>ns1.example</nsdname>
	  </ns>
	</rdata>
	<rdata>
	  <id>2</id>
	  <ns>
	    <nsdname>ns2.example</nsdname>
	  </ns>
	</rdata>
      </rrset>
      <rrset>
	<owner>example</owner>
	<type>ianadns:MX</type>
	<ttl>3600</ttl>
	<rdata>
	  <id>1</id>
	  <mx>
	    <preference>1</preference>
	    <exchange>xx.example</exchange>
	  </mx>
	</rdata>
      </rrset>
      <rrset>
	<owner>ns1.a.example</owner>
	<type>ianadns:A</type>
	<ttl>3600</ttl>
	<rdata>
	  <id>1</id>
	  <a>
	    <address>192.0.2.5</address>
	  </a>
	</rdata>
      </rrset>
      <rrset>
	<owner>ns2.a.example</owner>
	<type>ianadns:A</type>
	<ttl>3600</ttl>
	<rdata>
	  <id>1</id>
	  <a>
	    <address>192.0.2.6</address>
	  </a>
	</rdata>
      </rrset>
      <rrset>
	<owner>ns1.b.example</owner>
	<type>ianadns:A</type>
	<ttl>3600</ttl>
	<rdata>
	  <id>1</id>
	  <a>
	    <address>192.0.2.7</address>
	  </a>
	</rdata>
      </rrset>
      <rrset>
	<owner>ns2.b.example</owner>
	<type>ianadns:A</type>
	<ttl>3600</ttl>
	<rdata>
	  <id>1</id>
	  <a>
	    <address>192.0.2.8</address>
	  </a>
	</rdata>
      </rrset>
      <rrset>
	<owner>a.example</owner>
	<type>ianadns:NS</type>
	<ttl>3600</ttl>
	<rdata>
	  <id>1</id>
	  <ns>
	    <nsdname>ns1.a.example</nsdname>
	  </ns>
	</rdata>
	<rdata>
	  <id>2</id>
	  <ns>
	    <nsdname>ns2.a.example</nsdname>
	  </ns>
	</rdata>
      </rrset>
      <rrset>
	<owner>a.example</owner>
	<type>ianadns:DS</type>
	<ttl>3600</ttl>
	<rdata>
	  <id>1</id>
	  <ds>
	    <key-tag>57855</key-tag>
	    <algorithm>RSASHA1</algorithm>
	    <digest-type>SHA-1</digest-type>
	    <digest>B6DCD485719ADCA18E5F3D48A2331627FDD3636B</digest>
	  </ds>
	</rdata>
      </rrset>
      <rrset>
	<owner>*.a.example</owner>
	<type>ianadns:A</type>
	<ttl>3600</ttl>
	<rdata>
	  <id>1</id>
	  <a>
	    <address>192.0.2.11</address>
	  </a>
	</rdata>
      </rrset>
      <rrset>
	<owner>ai.example</owner>
	<type>ianadns:A</type>
	<ttl>3600</ttl>
	<rdata>
	  <id>1</id>
	  <a>
	    <address>192.0.2.9</address>
	  </a>
	</rdata>
      </rrset>
      <rrset>
	<owner>ai.example</owner>
	<type>ianadns:HINFO</type>
	<ttl>3600</ttl>
	<rdata>
	  <id>1</id>
	  <hinfo>
	    <cpu>KLH-10</cpu>
	    <os>ITS</os>
	  </hinfo>
	</rdata>
      </rrset>
      <rrset>
	<owner>ai.example</owner>
	<type>ianadns:AAAA</type>
	<ttl>3600</ttl>
	<rdata>
	  <id>1</id>
	  <aaaa>
	    <address>2001:db8::f00:baa9</address>
	  </aaaa>
	</rdata>
      </rrset>
      <rrset>
	<owner>b.example</owner>
	<type>ianadns:NS</type>
	<ttl>3600</ttl>
	<rdata>
	  <id>1</id>
	  <ns>
	    <nsdname>ns1.b.example</nsdname>
	  </ns>
	</rdata>
	<rdata>
	  <id>2</id>
	  <ns>
	    <nsdname>ns2.b.example</nsdname>
	  </ns>
	</rdata>
      </rrset>
      <rrset>
	<owner>ns1.example</owner>
	<type>ianadns:A</type>
	<ttl>3600</ttl>
	<rdata>
	  <id>1</id>
	  <a>
	    <address>192.0.2.1</address>
	  </a>
	</rdata>
      </rrset>
      <rrset>
	<owner>ns2.example</owner>
	<type>ianadns:A</type>
	<ttl>3600</ttl>
	<rdata>
	  <id>1</id>
	  <a>
	    <address>192.0.2.2</address>
	  </a>
	</rdata>
      </rrset>
      <rrset>
	<owner>*.w.example</owner>
	<type>ianadns:MX</type>
	<ttl>3600</ttl>
	<rdata>
	  <id>1</id>
	  <mx>
	    <preference>1</preference>
	    <exchange>ai.example</exchange>
	  </mx>
	</rdata>
      </rrset>
      <rrset>
	<owner>x.y.w.example</owner>
	<type>ianadns:MX</type>
	<ttl>3600</ttl>
	<rdata>
	  <id>1</id>
	  <mx>
	    <preference>1</preference>
	    <exchange>xx.example</exchange>
	  </mx>
	</rdata>
      </rrset>
      <rrset>
	<owner>xx.example</owner>
	<type>ianadns:A</type>
	<ttl>3600</ttl>
	<rdata>
	  <id>1</id>
	  <a>
	    <address>192.0.2.10</address>
	  </a>
	</rdata>
      </rrset>
      <rrset>
	<owner>xx.example</owner>
	<type>ianadns:HINFO</type>
	<ttl>3600</ttl>
	<rdata>
	  <id>1</id>
	  <hinfo>
	    <cpu>KLH-10</cpu>
	    <os>TOPS-20</os>
	  </hinfo>
	</rdata>
      </rrset>
      <rrset>
	<owner>xx.example</owner>
	<type>ianadns:AAAA</type>
	<ttl>3600</ttl>
	<rdata>
	  <id>1</id>
	  <aaaa>
	    <address>2001:db8::f00:baaa</address>
	  </aaaa>
	</rdata>
      </rrset>
      <rrset>
	<owner>x.w.example</owner>
	<type>ianadns:MX</type>
	<ttl>3600</ttl>
	<rdata>
	  <id>1</id>
	  <mx>
	    <preference>1</preference>
	    <exchange>xx.example</exchange>
	  </mx>
	</rdata>
      </rrset>
      <rrset>
	<owner>*.to-apex.example</owner>
	<type>ianadns:CNAME</type>
	<ttl>3600</ttl>
	<rdata>
	  <id>1</id>
	  <cname>
	    <cname>example</cname>
	  </cname>
	  <description>Wildcard expansion leading to apex</description>
	</rdata>
      </rrset>
      <rrset>
	<owner>*.to-nxdomain.example</owner>
	<type>ianadns:CNAME</type>
	<ttl>3600</ttl>
	<rdata>
	  <id>1</id>
	  <cname>
	    <cname>nxdomain.example</cname>
	  </cname>
	  <description>Wildcard expansion leading to nonexistent name.</description>
	</rdata>
      </rrset>
    </zone>
  </zones>
</config>
